tubemp3/__init__.py
tubemp3/api_deizer.py
tubemp3/file.py
tubemp3/in_line.py
tubemp3/metadata.py
tubemp3-0.4.2.dist-info/licenses/LICENSE
tubemp3-0.4.2.dist-info/METADATA
tubemp3-0.4.2.dist-info/WHEEL
tubemp3-0.4.2.dist-info/entry_points.txt
tubemp3-0.4.2.dist-info/top_level.txt
tubemp3-0.4.2.dist-info/RECORD
