Metadata-Version: 2.4
Name: tubemp3
Version: 0.4.2
Summary: Library for getting music and video in high quality from YouTube
Home-page: https://github.com/reinanbr/tubemp3
Author: Reinan Br
Author-email: slimchatuba@gmail.com
License: MIT License
Keywords: video mp3 m4a mp4 youtube music download
License-File: LICENSE
Requires-Dist: tqdm
Requires-Dist: mutagen
Requires-Dist: requests
Requires-Dist: yt-dlp
Dynamic: author
Dynamic: author-email
Dynamic: description
Dynamic: description-content-type
Dynamic: home-page
Dynamic: keywords
Dynamic: license
Dynamic: license-file
Dynamic: requires-dist
Dynamic: summary
